[
  {
    "id": 1,
    "name": "نيرو كريت دبليو بى",
    "description": "إضافة سائلة بنية اللون خالية من الكلوريدات ",
    "price": 1500
  },
  {
    "id": 1,
    "name": "نيرو بـوند",
    "description": "مستحلب أبيض من الاسترين بيوتادين المعدل.",
    "price": 800
  },

  {
    "id": 101,
    "name": "نيــرو هـارد تـوب",
    "description": "خليط جاهز للاستعمال مكون من أسمنت و إضافات وركام صلب.",
    "price": 300
  },
  {
    "id": 101,
    "name": "نيــرو ميتـال تـوب",
    "description": "خليط جاهز للاستعمال مكون من أسمنت و إضافات وركام معدني",
    "price": 150
  },
  {
    "id": 101,
    "name": "نيرو هارد توب",
    "categoryId": 2,
    "description": "خليط جاهز للاستعمال مكون من أسمنت و إضافات وركام معدني",
    "price": 150
  },
  {
    "id": 2,
    "name": "نيرو كوراندم",
    "categoryId": 2,
    "description": "خليط جاهز للاستعمال مكون من أسمنت و إضافات وركام معدني",
    "price": 150
  },
  {
    "id": 2,
    "name": "نيــرو ميتـال تـوب",
    "description": "خليط جاهز للاستعمال مكون من أسمنت و إضافات وركام معدني",
    "price": 150
  },
  {
    "id": 3,
    "name": "نيرو سيمنت سيلف",
    "description": "خليط جاهز للاستعمال مكون من أسمنت و إضافات وركام معدني",
    "price": 150
  }
]
